{
    "key": "group_5d78f84109e2b",
    "title": "[Gutenberg] Слайдер",
    "fields": [
        {
            "key": "field_5d78f84524374",
            "label": "Слайды",
            "name": "slides",
            "type": "repeater",
            "instructions": "",
            "required": 0,
            "conditional_logic": 0,
            "wrapper": {
                "width": "",
                "class": "",
                "id": ""
            },
            "collapsed": "field_5d78f86a24376",
            "min": 0,
            "max": 0,
            "layout": "block",
            "button_label": "Добавить слайд",
            "sub_fields": [
                {
                    "key": "field_5d86894d0ca06",
                    "label": "Фоновое изображение",
                    "name": "bg_image",
                    "type": "image",
                    "instructions": "",
                    "required": 0,
                    "conditional_logic": 0,
                    "wrapper": {
                        "width": "",
                        "class": "",
                        "id": ""
                    },
                    "return_format": "id",
                    "preview_size": "extra_large",
                    "library": "all",
                    "min_width": "",
                    "min_height": "",
                    "min_size": "",
                    "max_width": "",
                    "max_height": "",
                    "max_size": "",
                    "mime_types": ""
                },
                {
                    "key": "field_5d8688ef225e7",
                    "label": "Темный текст",
                    "name": "dark_text",
                    "type": "true_false",
                    "instructions": "",
                    "required": 0,
                    "conditional_logic": 0,
                    "wrapper": {
                        "width": "",
                        "class": "",
                        "id": ""
                    },
                    "message": "",
                    "default_value": 0,
                    "ui": 0,
                    "ui_on_text": "",
                    "ui_off_text": ""
                },
                {
                    "key": "field_5d78f85d24375",
                    "label": "Надзаголовок",
                    "name": "overtitle",
                    "type": "text",
                    "instructions": "",
                    "required": 0,
                    "conditional_logic": 0,
                    "wrapper": {
                        "width": "",
                        "class": "",
                        "id": ""
                    },
                    "default_value": "",
                    "placeholder": "",
                    "prepend": "",
                    "append": "",
                    "maxlength": ""
                },
                {
                    "key": "field_5d78f86a24376",
                    "label": "Заголовок",
                    "name": "title",
                    "type": "text",
                    "instructions": "",
                    "required": 0,
                    "conditional_logic": 0,
                    "wrapper": {
                        "width": "",
                        "class": "",
                        "id": ""
                    },
                    "default_value": "",
                    "placeholder": "",
                    "prepend": "",
                    "append": "",
                    "maxlength": ""
                },
                {
                    "key": "field_5d78f87c24377",
                    "label": "Описание",
                    "name": "description",
                    "type": "wysiwyg",
                    "instructions": "",
                    "required": 0,
                    "conditional_logic": 0,
                    "wrapper": {
                        "width": "",
                        "class": "",
                        "id": ""
                    },
                    "default_value": "",
                    "tabs": "all",
                    "toolbar": "full",
                    "media_upload": 1,
                    "delay": 0
                },
                {
                    "key": "field_5d78f88424378",
                    "label": "Кнопка",
                    "name": "button",
                    "type": "group",
                    "instructions": "",
                    "required": 0,
                    "conditional_logic": 0,
                    "wrapper": {
                        "width": "",
                        "class": "",
                        "id": ""
                    },
                    "layout": "block",
                    "sub_fields": [
                        {
                            "key": "field_5d78f89124379",
                            "label": "Тип кнопки",
                            "name": "type",
                            "type": "select",
                            "instructions": "",
                            "required": 1,
                            "conditional_logic": 0,
                            "wrapper": {
                                "width": "",
                                "class": "",
                                "id": ""
                            },
                            "choices": {
                                "callrequest": "Кнопка обратного звонка",
                                "link": "Ссылка",
                                "none": "Без кнопки"
                            },
                            "default_value": [
                                "callrequest"
                            ],
                            "allow_null": 0,
                            "multiple": 0,
                            "ui": 0,
                            "return_format": "value",
                            "ajax": 0,
                            "placeholder": ""
                        },
                        {
                            "key": "field_5d78f8eb2437a",
                            "label": "Текст кнопки",
                            "name": "text",
                            "type": "text",
                            "instructions": "",
                            "required": 1,
                            "conditional_logic": 0,
                            "wrapper": {
                                "width": "",
                                "class": "",
                                "id": ""
                            },
                            "default_value": "Заказать",
                            "placeholder": "Заказать",
                            "prepend": "",
                            "append": "",
                            "maxlength": ""
                        },
                        {
                            "key": "field_5d78f9072437b",
                            "label": "Ссылка",
                            "name": "link",
                            "type": "link",
                            "instructions": "",
                            "required": 0,
                            "conditional_logic": [
                                [
                                    {
                                        "field": "field_5d78f89124379",
                                        "operator": "==",
                                        "value": "link"
                                    }
                                ]
                            ],
                            "wrapper": {
                                "width": "",
                                "class": "",
                                "id": ""
                            },
                            "return_format": "array"
                        }
                    ]
                }
            ]
        }
    ],
    "location": [
        [
            {
                "param": "block",
                "operator": "==",
                "value": "acf\/hero-slider"
            }
        ]
    ],
    "menu_order": 0,
    "position": "normal",
    "style": "default",
    "label_placement": "top",
    "instruction_placement": "label",
    "hide_on_screen": "",
    "active": 1,
    "description": "",
    "modified": 1569500263
}